husqvarna_automower/__init__.py
husqvarna_automower-2021.3.2.dist-info/LICENSE
husqvarna_automower-2021.3.2.dist-info/METADATA
husqvarna_automower-2021.3.2.dist-info/WHEEL
husqvarna_automower-2021.3.2.dist-info/top_level.txt
husqvarna_automower-2021.3.2.dist-info/RECORD
