Metadata-Version: 2.1
Name: husqvarna-automower
Version: 2021.3.2
Summary: module to communicate to Husqvarna Automower API
Home-page: https://github.com/Thomas55555/husqvarna_automower_py
Author: Thomas Protzner
Author-email: thomas.protzner@gmail.com
License: Apache License 2.0
Platform: UNKNOWN
Classifier: Programming Language :: Python :: 3
Classifier: License :: OSI Approved :: Apache Software License
Classifier: Operating System :: OS Independent
Requires-Dist: aiohttp
